PySuperDropletLES/__init__.py
PySuperDropletLES-0.0.0.dist-info/LICENSE
PySuperDropletLES-0.0.0.dist-info/METADATA
PySuperDropletLES-0.0.0.dist-info/WHEEL
PySuperDropletLES-0.0.0.dist-info/top_level.txt
PySuperDropletLES-0.0.0.dist-info/RECORD
