Metadata-Version: 2.1
Name: PySuperDropletLES
Version: 0.0.0
Summary: TODO
License: GPL-3.0
Keywords: TODO,TODO
Classifier: Intended Audience :: Science/Research
Classifier: License :: OSI Approved :: GNU General Public License v3 (GPLv3)
Classifier: Operating System :: OS Independent
Classifier: Programming Language :: Python :: 3
Classifier: Topic :: Scientific/Engineering
Classifier: Topic :: Scientific/Engineering :: Atmospheric Science
Classifier: Topic :: Scientific/Engineering :: Mathematics
Classifier: Topic :: Scientific/Engineering :: Physics
Requires-Python: >=3.10
License-File: LICENSE
Requires-Dist: numba-mpi (>=0.14)
Requires-Dist: PySDM
Requires-Dist: PyMPDATA
